{
    "CTk": {
      "fg_color": "gray14"
    },
    "CTkFrame": {
      "corner_radius": 10,
      "border_width": 0,
      "fg_color": "gray13",
      "top_fg_color": "gray16",
      "border_color": "gray28"
    },
    "CTkButton": {
      "corner_radius": 10,
      "border_width": 1,
      "fg_color": "transparent",
      "hover_color": "gray50",
      "border_color": "#949A9F",
      "text_color": "#DCE4EE",
      "text_color_disabled": "gray60"
    },
    "CTkLabel": {
      "corner_radius": 0,
      "fg_color": "transparent",
      "text_color": "gray84"
    },
    "CTkEntry": {
      "corner_radius": 10,
      "border_width": 1,
      "fg_color": "#343638",
      "border_color": "#565B5E",
      "text_color": "gray84",
      "placeholder_text_color": "gray62"
    },
    "CTkCheckbox": {
      "corner_radius": 6,
      "border_width": 3,
      "fg_color": "#1f538d",
      "border_color": "#949A9F",
      "hover_color": "#14375e",
      "checkmark_color": "gray90",
      "text_color": "gray84",
      "text_color_disabled": "gray45"
    },
    "CTkProgressBar": {
      "corner_radius": 1000,
      "border_width": 0,
      "fg_color": "#4A4D50",
      "progress_color": "green",
      "border_color": "gray"
    },
    "CTkOptionMenu": {
      "corner_radius": 10,
      "fg_color": "#343638",
      "button_color": "#565B5E",
      "button_hover_color": "#7A848D",
      "text_color": "#DCE4EE",
      "text_color_disabled": "gray60"
    },
    "CTkSegmentedButton": {
      "corner_radius": 10,
      "border_width": 2,
      "fg_color": "gray29",
      "selected_color": "gray29",
      "selected_hover_color": "gray29",
      "unselected_color": "gray29",
      "unselected_hover_color": "gray41",
      "text_color": "#DCE4EE",
      "text_color_disabled": "gray60"
    },
    "DropdownMenu": {
      "fg_color": "gray20",
      "hover_color": "gray28",
      "text_color": "gray84"
    },
    "CTkFont": {
      "macOS": {
        "family": "SF Display",
        "size": 13,
        "weight": "normal"
      },
      "Windows": {
        "family": "Roboto",
        "size": 13,
        "weight": "normal"
      },
      "Linux": {
        "family": "Roboto",
        "size": 13,
        "weight": "normal"
      }
    }
  }
  